fibrenest_db_models/__init__.py
fibrenest_db_models/all.py
fibrenest_db_models/common.py
fibrenest_db_models/old.py
fibrenest_db_models/postgres.py
fibrenest_db_models-21.11.dist-info/LICENSE.txt
fibrenest_db_models-21.11.dist-info/METADATA
fibrenest_db_models-21.11.dist-info/WHEEL
fibrenest_db_models-21.11.dist-info/top_level.txt
fibrenest_db_models-21.11.dist-info/RECORD
