Metadata-Version: 2.1
Name: fibrenest-db-models
Version: 21.11
Summary: DB schema and sqlalchemy db models for fibrenest
Home-page: https://gitlab.com/horsebridge/fibrenest_db_models.git
Author: Nitin Sidhu
Author-email: nitin.sidhu23@gmail.com
License: MIT
Platform: UNKNOWN
Classifier: License :: OSI Approved :: MIT License
Classifier: Operating System :: OS Independent
Classifier: Programming Language :: Python :: 3.6
Classifier: Programming Language :: Python :: 3.7
Classifier: Programming Language :: Python :: 3.8
Requires-Python: ~=3.6
License-File: LICENSE.txt
Requires-Dist: sqlalchemy
